lovadira/__init__.py
lovadira/generator.py
lovadira/utils.py
test/__init__.py
test/test_generator.py
lovadira-0.1.dist-info/LICENSE
lovadira-0.1.dist-info/LICENSE_JAWA
lovadira-0.1.dist-info/METADATA
lovadira-0.1.dist-info/WHEEL
lovadira-0.1.dist-info/top_level.txt
lovadira-0.1.dist-info/RECORD
