Metadata-Version: 2.1
Name: lovadira
Version: 0.1
Summary: A library for generating random quotes from Gus Baha
Home-page: https://github.com/Anammkh/Lovadira
Author: Khoirul Anam
Author-email: khoirulanaam4567@gmail.com
Classifier: Programming Language :: Python :: 3
Classifier: License :: OSI Approved :: MIT License
Classifier: Operating System :: OS Independent
Requires-Python: >=3.6
License-File: LICENSE
License-File: LICENSE_JAWA
